koota/__init__.py
koota/main_script.py
koota/mario.py
koota/naruto.py
koota-0.0.2.dist-info/LICENSE
koota-0.0.2.dist-info/METADATA
koota-0.0.2.dist-info/WHEEL
koota-0.0.2.dist-info/top_level.txt
koota-0.0.2.dist-info/RECORD
