Metadata-Version: 2.1
Name: koota
Version: 0.0.2
Summary: Library for data analysis and EDA
Home-page: https://github.com/EvgenyIsmagilov/koota
Download-URL: https://github.com/EvgenyIsmagilov/koota/archive/refs/tags/0.0.2.tar.gz
Author: Evgeny Ismagilov
Author-email: evgenyismagilov@gmail.com
License: MIT
Keywords: EDA,DATA,CLEANING,analysis,koota
Platform: UNKNOWN
Classifier: Development Status :: 3 - Alpha
Classifier: Topic :: Software Development :: Build Tools
Classifier: License :: OSI Approved :: MIT License
Classifier: Programming Language :: Python :: 3
Classifier: Programming Language :: Python :: 3.4
Classifier: Programming Language :: Python :: 3.5
Classifier: Programming Language :: Python :: 3.6
License-File: LICENSE
Requires-Dist: pandas (==0.24)
Requires-Dist: unidecode
Requires-Dist: scikit-learn (==1.0.2)
